skyant/scrapper/__init__.py
skyant/scrapper/_field.py
skyant/scrapper/_loader.py
skyant/scrapper/catalog/__init__.py
skyant/scrapper/catalog/_item.py
skyant/scrapper/catalog/_router.py
skyant/scrapper/catalog/_search.py
skyant_scrapper-0.0.2.dist-info/LICENSE
skyant_scrapper-0.0.2.dist-info/METADATA
skyant_scrapper-0.0.2.dist-info/WHEEL
skyant_scrapper-0.0.2.dist-info/top_level.txt
skyant_scrapper-0.0.2.dist-info/RECORD
