Metadata-Version: 2.1
Name: skyant-scrapper
Version: 0.0.2
Summary: Hi-Level fields.
Home-page: https://skyant.dev
Author: Iurii Tarasenko
Author-email: info@skyant.dev
License: MIT
Project-URL: Source & issues, https://gitlab.com/skyant/python/scrapper
Project-URL: Documentation, https://docs.skyant.dev/projects/shell
Keywords: fields,web scrapping
Classifier: Programming Language :: Python :: 3.10
Classifier: Intended Audience :: Developers
Classifier: Intended Audience :: Information Technology
Classifier: Topic :: Software Development :: Libraries :: Python Modules
Requires-Python: >=3.10
License-File: LICENSE
Requires-Dist: selenium
Requires-Dist: webdriver-manager
Requires-Dist: skyant-data
Requires-Dist: validators
Requires-Dist: lxml
